Workbook

Sheet Cover
B6: Practical Skills Module: Financial Modeling
B12: Blu Containers Company
B13: =TODAY() -> 46215
B24: Financial Model Worksheet - Vertical Orientation | H24: Powered by:

Sheet Summary
B1: =Cover!B12 -> Blu Containers Company
B2: Summary Outputs
C5: SUMMARY VALUES - BASE CASE | T5: ="SUMMMARY VALUES - "&UPPER(CHOOSE(Scenarios!$D$6,Scenarios!C14,Scenarios!C15,Scenarios!C16)) -> SUMMMARY VALUES - BASE CASE
K6: Projected | AA6: Projected
D7: ($ Millions) | F7: Trend | H7: =X7 -> 2020 | I7: =Y7 -> 2021 | J7: =Z7 -> 2022 | K7: =AA7 -> 2023 | L7: =AB7 -> 2024 | M7: =AC7 -> 2025 | N7: =AD7 -> 2026 | O7: =AE7 -> 2027 | X7: =Model!H7 -> 2020 | Y7: =Model!I7 -> 2021 | Z7: =Model!J7 -> 2022 | AA7: =Model!K7 -> 2023 | AB7: =Model!L7 -> 2024 | AC7: =Model!M7 -> 2025 | AD7: =Model!N7 -> 2026 | AE7: =Model!O7 -> 2027
D10: Income Statement Items | U10: Income Statement Items
E12: Net Revenue | H12: 213.5 | I12: 236.6 | J12: 204.8 | K12: 252.4621 | L12: 233.58111 | M12: 281.23111 | N12: 281.22955 | O12: 268.17287 | V12: Net Revenue | W12: (MM) | X12: =Model!H85 -> 213.5 | Y12: =Model!I85 -> 236.6 | Z12: =Model!J85 -> 204.8 | AA12: =Model!K85 -> 252.4621 | AB12: =Model!L85 -> 233.58111 | AC12: =Model!M85 -> 281.23111 | AD12: =Model!N85 -> 281.22955 | AE12: =Model!O85 -> 268.17287
E13: Growth | I13: 0.10819672 | J13: -0.13440406 | K13: 0.23272508 | L13: -0.074787393 | M13: 0.20399763 | N13: -5.5263805e-06 | O13: -0.04642714 | V13: Growth | W13: (%) | Y13: =Y12/X12-1 -> 0.10819672 | Z13: =Z12/Y12-1 -> -0.13440406 | AA13: =AA12/Z12-1 -> 0.23272508 | AB13: =AB12/AA12-1 -> -0.074787393 | AC13: =AC12/AB12-1 -> 0.20399763 | AD13: =AD12/AC12-1 -> -5.5263805e-06 | AE13: =AE12/AD12-1 -> -0.04642714
E16: EBITDA | H16: 50.2 | I16: 68.4 | J16: 33.1 | K16: 73.875242 | L16: 47.110499 | M16: 86.456886 | N16: 76.709885 | O16: 54.342096 | V16: EBITDA | W16: (MM) | X16: =Model!H92 -> 50.2 | Y16: =Model!I92 -> 68.4 | Z16: =Model!J92 -> 33.1 | AA16: =Model!K92 -> 73.875242 | AB16: =Model!L92 -> 47.110499 | AC16: =Model!M92 -> 86.456886 | AD16: =Model!N92 -> 76.709885 | AE16: =Model!O92 -> 54.342096
E17: Margin | H17: 0.23512881 | I17: 0.28909552 | J17: 0.16162109 | K17: 0.29261914 | L17: 0.20168796 | M17: 0.30742291 | N17: 0.27276609 | O17: 0.2026383 | V17: Margin | W17: (%) | X17: =X16/X12 -> 0.23512881 | Y17: =Y16/Y12 -> 0.28909552 | Z17: =Z16/Z12 -> 0.16162109 | AA17: =AA16/AA12 -> 0.29261914 | AB17: =AB16/AB12 -> 0.20168796 | AC17: =AC16/AC12 -> 0.30742291 | AD17: =AD16/AD12 -> 0.27276609 | AE17: =AE16/AE12 -> 0.2026383
E18: Growth | I18: 0.3625498 | J18: -0.51608187 | K18: 1.2318804 | L18: -0.36229652 | M18: 0.83519358 | N18: -0.11273829 | O18: -0.29158939 | V18: Growth | W18: (%) | Y18: =Y16/X16-1 -> 0.3625498 | Z18: =Z16/Y16-1 -> -0.51608187 | AA18: =AA16/Z16-1 -> 1.2318804 | AB18: =AB16/AA16-1 -> -0.36229652 | AC18: =AC16/AB16-1 -> 0.83519358 | AD18: =AD16/AC16-1 -> -0.11273829 | AE18: =AE16/AD16-1 -> -0.29158939
E21: Net Income | H21: 14.1 | I21: 23.7 | J21: 2.2 | K21: 29.705374 | L21: 12.883787 | M21: 38.802359 | N21: 33.318879 | O21: 19.418162 | V21: Net Income | W21: (MM) | X21: =Model!H104 -> 14.1 | Y21: =Model!I104 -> 23.7 | Z21: =Model!J104 -> 2.2 | AA21: =Model!K104 -> 29.705374 | AB21: =Model!L104 -> 12.883787 | AC21: =Model!M104 -> 38.802359 | AD21: =Model!N104 -> 33.318879 | AE21: =Model!O104 -> 19.418162
E22: Margin | H22: 0.066042155 | I22: 0.10016906 | J22: 0.010742187 | K22: 0.11766271 | L22: 0.055157659 | M22: 0.13797321 | N22: 0.11847574 | O22: 0.072409123 | V22: Margin | W22: (%) | X22: =X21/X12 -> 0.066042155 | Y22: =Y21/Y12 -> 0.10016906 | Z22: =Z21/Z12 -> 0.010742187 | AA22: =AA21/AA12 -> 0.11766271 | AB22: =AB21/AB12 -> 0.055157659 | AC22: =AC21/AC12 -> 0.13797321 | AD22: =AD21/AD12 -> 0.11847574 | AE22: =AE21/AE12 -> 0.072409123
E23: Growth | I23: 0.68085106 | J23: -0.907173 | K23: 12.502443 | L23: -0.56628092 | M23: 2.0117199 | N23: -0.14131822 | O23: -0.41720241 | V23: Growth | W23: (%) | Y23: =Y21/X21-1 -> 0.68085106 | Z23: =Z21/Y21-1 -> -0.907173 | AA23: =AA21/Z21-1 -> 12.502443 | AB23: =AB21/AA21-1 -> -0.56628092 | AC23: =AC21/AB21-1 -> 2.0117199 | AD23: =AD21/AC21-1 -> -0.14131822 | AE23: =AE21/AD21-1 -> -0.41720241
U25: Balance sheet
C26: SUMMARY VALUES - BEST CASE | V26: Senior Secured Term Debt | W26: (MM) | X26: =Model!H177 -> 250 | Y26: =Model!I177 -> 225 | Z26: =Model!J177 -> 200 | AA26: =Model!K177 -> 175 | AB26: =Model!L177 -> 150 | AC26: =Model!M177 -> 125 | AD26: =Model!N177 -> 100 | AE26: =Model!O177 -> 75
K27: Projected | V27: Growth | W27: (%) | Y27: =Y26/X26-1 -> -0.1 | Z27: =Z26/Y26-1 -> -0.11111111 | AA27: =AA26/Z26-1 -> -0.125 | AB27: =AB26/AA26-1 -> -0.14285714 | AC27: =AC26/AB26-1 -> -0.16666667 | AD27: =AD26/AC26-1 -> -0.2 | AE27: =AE26/AD26-1 -> -0.25
D28: ($ Millions) | F28: Trend | H28: =H7 -> 2020 | I28: =I7 -> 2021 | J28: =J7 -> 2022 | K28: =K7 -> 2023 | L28: =L7 -> 2024 | M28: =M7 -> 2025 | N28: =N7 -> 2026 | O28: =O7 -> 2027 | V28: Bank Debt - Revolver | W28: (MM) | X28: =Model!H171 -> 0 | Y28: =Model!I171 -> 0 | Z28: =Model!J171 -> 0 | AA28: =Model!K171 -> 1.0770176 | AB28: =Model!L171 -> 7.7435851 | AC28: =Model!M171 -> 1.2289546 | AD28: =Model!N171 -> 0 | AE28: =Model!O171 -> 2.6139756
V29: Growth | W29: (%) | Y29: =IFERROR(Y28/X28-1, "") | Z29: =IFERROR(Z28/Y28-1, "") | AA29: =IFERROR(AA28/Z28-1, "") | AB29: =IFERROR(AB28/AA28-1, "") -> 6.1898407 | AC29: =IFERROR(AC28/AB28-1, "") -> -0.84129384 | AD29: =IFERROR(AD28/AC28-1, "") -> -1 | AE29: =IFERROR(AE28/AD28-1, "")
D31: Income Statement Items | V31: Shareholder's Equity | W31: (MM) | X31: =Model!H184 -> 239.7 | Y31: =Model!I184 -> 258.7 | Z31: =Model!J184 -> 258.5 | AA31: =Model!K184 -> 282.2643 | AB31: =Model!L184 -> 292.57133 | AC31: =Model!M184 -> 323.61322 | AD31: =Model!N184 -> 350.26832 | AE31: =Model!O184 -> 365.80285
V32: Growth | W32: (%) | Y32: =Y31/X31-1 -> 0.079265749 | Z32: =Z31/Y31-1 -> -0.00077309625 | AA32: =AA31/Z31-1 -> 0.091931525 | AB32: =AB31/AA31-1 -> 0.036515528 | AC32: =AC31/AB31-1 -> 0.10610024 | AD32: =AD31/AC31-1 -> 0.082367165 | AE32: =AE31/AD31-1 -> 0.044350371
E33: Net Revenue | H33: 213.5 | I33: 236.6 | J33: 204.8 | K33: 264.10863 | L33: 244.64312 | M33: 297.21532 | N33: 300.41838 | O33: 281.50084
E34: Growth | I34: 0.10819672 | J34: -0.13440406 | K34: 0.28959292 | L34: -0.073702679 | M34: 0.21489344 | N34: 0.010776922 | O34: -0.062970636
E37: EBITDA | H37: 50.2 | I37: 68.4 | J37: 33.1 | K37: 85.521774 | L37: 58.538129 | M37: 102.0651 | N37: 95.265445 | O37: 70.580713
E38: Margin | H38: 0.23512881 | I38: 0.28909552 | J38: 0.16162109 | K38: 0.32381287 | L38: 0.23927969 | M38: 0.34340456 | N38: 0.31710924 | O38: 0.25073002
E39: Growth | I39: 0.3625498 | J39: -0.51608187 | K39: 1.5837394 | L39: -0.31551784 | M39: 0.74356608 | N39: -0.066620723 | O39: -0.25911528
E42: Net Income | H42: 14.1 | I42: 23.7 | J42: 2.2 | K42: 37.27562 | L42: 20.35375 | M42: 49.249695 | N42: 45.427923 | O42: 29.973263
E43: Margin | H43: 0.066042155 | I43: 0.10016906 | J43: 0.010742187 | K43: 0.14113746 | L43: 0.083197723 | M43: 0.16570376 | N43: 0.15121552 | O43: 0.10647664
E44: Growth | I44: 0.68085106 | J44: -0.907173 | K44: 15.943464 | L44: -0.45396615 | M44: 1.4196865 | N44: -0.077599927 | O44: -0.34020176
C47: SUMMARY VALUES - WORST CASE
K48: Projected
D49: ($ Millions) | F49: Trend | H49: =H28 -> 2020 | I49: =I28 -> 2021 | J49: =J28 -> 2022 | K49: =K28 -> 2023 | L49: =L28 -> 2024 | M49: =M28 -> 2025 | N49: =N28 -> 2026 | O49: =O28 -> 2027
D52: Income Statement Items
E53: Net Revenue | H53: 213.5 | I53: 236.6 | J53: 204.8 | K53: 238.41461 | L53: 220.17079 | M53: 262.60854 | N53: 259.93619 | O53: 244.66998
E54: Growth | I54: 0.10819672 | J54: -0.13440406 | K54: 0.16413383 | L54: -0.076521412 | M54: 0.19274926 | N54: -0.010176171 | O54: -0.058730611
E57: EBITDA | H57: 50.2 | I57: 68.4 | J57: 33.1 | K57: 60.834295 | L57: 33.859072 | M57: 68.207666 | N57: 57.052628 | O57: 34.164574
E58: Margin | H58: 0.23512881 | I58: 0.28909552 | J58: 0.16162109 | K58: 0.25516178 | L58: 0.15378549 | M58: 0.25973133 | N58: 0.21948705 | O58: 0.13963533
E59: Growth | I59: 0.3625498 | J59: -0.51608187 | K59: 0.83789411 | L59: -0.44342132 | M59: 1.0144577 | N59: -0.16354523 | O59: -0.40117441
E62: Net Income | H62: 14.1 | I62: 23.7 | J62: 2.2 | K62: 21.228758 | L62: 4.0836355 | M62: 26.465119 | N62: 19.699196 | O62: 5.1078377
E63: Margin | H63: 0.066042155 | I63: 0.10016906 | J63: 0.010742187 | K63: 0.089041349 | L63: 0.018547581 | M63: 0.10077783 | N63: 0.075784738 | O63: 0.020876438
E64: Growth | I64: 0.68085106 | J64: -0.907173 | K64: 8.6494356 | L64: -0.80763663 | M64: 5.480774 | N64: -0.25565434 | O64: -0.74070832
C67: SUMMARY VALUES - BASE CASE
K68: Projected
D69: ($ Millions) | F69: Trend | H69: =H49 -> 2020 | I69: =I49 -> 2021 | J69: =J49 -> 2022 | K69: =K49 -> 2023 | L69: =L49 -> 2024 | M69: =M49 -> 2025 | N69: =N49 -> 2026 | O69: =O49 -> 2027
D72: Capital Structure
E73: Senior Secured Term Debt | H73: 250 | I73: 225 | J73: 200 | K73: 175 | L73: 150 | M73: 125 | N73: 100 | O73: 75
E74: Growth | I74: -0.1 | J74: -0.11111111 | K74: -0.125 | L74: -0.14285714 | M74: -0.16666667 | N74: -0.2 | O74: -0.25
E77: Bank Debt - Revolver | H77: 0 | I77: 0 | J77: 0 | K77: 1.0770176 | L77: 7.7435851 | M77: 1.2289546 | N77: 0 | O77: 2.6139756
E78: Growth | L78: 6.1898407 | M78: -0.84129384 | N78: -1
E81: Shareholder's Equity | H81: 239.7 | I81: 258.7 | J81: 258.5 | K81: 282.2643 | L81: 292.57133 | M81: 323.61322 | N81: 350.26832 | O81: 365.80285
E82: Growth | I82: 0.079265749 | J82: -0.00077309625 | K82: 0.091931525 | L82: 0.036515528 | M82: 0.10610024 | N82: 0.082367165 | O82: 0.044350371
C85: VISUAL REPRESENTATION OF MAIN INDICATORS

Sheet Assumptions
B1: =Cover!B12 -> Blu Containers Company
B2: Inputs and Assumptions
C5: GENERAL | J5: EQUITY
C8: - | D8: First year of forecast in financial model: | G8: 2023 | J8: ="Stock Price - "&TEXT(TODAY()-1,"mm/dd/yy") -> Stock Price - 07/dd/yy | N8: 11.5
C9: - | D9: Three scenarios have been used for Inflation, Product Pricing | J9: ="Fully Diluted Shares O/S (MM) - Dec. 31, "&G8-1 -> Fully Diluted Shares O/S (MM) - Dec. 31, 2022 | N9: 14.8
D10: and sales volume growth | J10: Common Dividend Payout Rate | N10: 0.2
C13: PRODUCT PRICING | J13: OPERATIONS
C16: - | D16: The product pricing cases used in the model are as follows:
C17: Pricing Case | E17: =Scenarios!G6&" - "&Scenarios!K6 -> 2023 - 2027 | J17: Annual Factory Capacity (000's units): | N17: 420
C18: Base Case | E18: Research Forecast
C19: Best Case | F19: 0.04 | J19: Capacity Constraints - reached opearting rate | N19: =MAX(Model!O22) -> 1 | O19: conditional formating
C20: Worst Case | F20: -0.04
C23: COSTS | J23: INTEREST RATES
C26: Cost Item | E26: =G8 -> 2023 | G26: Increases
C27: Raw Materials | E27: 226 | F27: per Unit | G27: Inflation on a unit basis | J27: Interest earned on Cash balances: | N27: 0.01
C28: Utilities | E28: 66.2 | F28: per Unit | G28: Inflation on a unit basis | J28: Interest rate on Bank Revolver: | N28: 0.06
C29: Rent | E29: 23.5 | F29: MM | G29: Inflation on a total basis | J29: Interest rate on Senior Secured Term Debt: | N29: 0.06
C30: Operating Labour | E30: 43.5 | F30: MM | G30: Inflation on a total basis
C31: Other | E31: 2 | F31: MM | G31: Inflation on a total basis
C32: SG&A | E32: 3.9 | F32: MM | G32: Inflation on a total basis
C35: DEPRECIATION | J35: TAXES
C38: - | D38: Depreciation Methodology Used: | H38: Straight Line
C39: - | D39: Years remaining for depreciation of existing assets: | H39: 25 | J39: Tax rate assumed in the model: | N39: 0.35
C40: - | D40: Years used for depreciation of new assets: | H40: 30 | J40: Additional tax assumptions in "Other Assumptions" box
B44: =Summary!B1 -> Blu Containers Company
B45: Inputs and Assumptions
C48: OTHER ASSUMPTIONS | J48: =G8 -> 2023 | K48: =J48+1 -> 2024 | L48: =K48+1 -> 2025 | M48: =L48+1 -> 2026 | N48: =M48+1 -> 2027
C52: Income Statement
D53: Cost Adjustments - Gain/(Loss) | G53: MM | J53: 0 | K53: 0 | L53: 0 | M53: 0 | N53: 0
C55: Cash Flow Statement
D56: Investing Activities - Other | G56: MM | J56: 0 | K56: 0 | L56: 0 | M56: 0 | N56: 0
C58: Capital Expenditures | G58: MM | J58: 16 | K58: 17 | L58: 17.3 | M58: 17.5 | N58: 18
C60: Income Tax
D61: Reduction in EBT for timing differences | G61: MM | J61: 5 | K61: 5 | L61: 5 | M61: 5 | N61: 5
C63: Working Capital Days
D64: Accounts Receivable | G64: days | J64: 48 | K64: 44 | L64: 40 | M64: 40 | N64: 40
D65: Inventories | G65: days | J65: 70 | K65: 65 | L65: 60 | M65: 60 | N65: 55
D66: Prepaid Expenses | G66: days | J66: 30 | K66: 30 | L66: 30 | M66: 30 | N66: 30
D67: Other Assets | G67: days | J67: 3 | K67: 3 | L67: 3 | M67: 3 | N67: 3
D68: Accounts Payable | G68: days | J68: 40 | K68: 40 | L68: 40 | M68: 40 | N68: 40
D69: Other Liabilities | G69: days | J69: 10 | K69: 10 | L69: 10 | M69: 10 | N69: 10
C71: Change in Debt & Equity
D72: Senior Term Debt Issuance / (Repayment) | G72: MM | J72: -25 | K72: -25 | L72: -25 | M72: -25 | N72: -25
D73: Common Stock Issuance / (Buy-back) | G73: MM | J73: 0 | K73: 0 | L73: 0 | M73: 0 | N73: 0

Sheet Scenarios
B1: =Assumptions!B1 -> Blu Containers Company
B2: Economic and Sales Scenarios
B6: SCENARIO SWITCH: | D6: 1 | G6: =Assumptions!G8 -> 2023 | H6: =G6+1 -> 2024 | I6: =H6+1 -> 2025 | J6: =I6+1 -> 2026 | K6: =J6+1 -> 2027
D9: Base Case
B10: ECONOMIC SCENARIOS
B12: Cost Inflation | D12: LIVE CASE -> | G12: =CHOOSE($D$6,G14,G15,G16) -> 0.02 | H12: =CHOOSE($D$6,H14,H15,H16) -> 0.02 | I12: =CHOOSE($D$6,I14,I15,I16) -> 0.02 | J12: =CHOOSE($D$6,J14,J15,J16) -> 0.025 | K12: =CHOOSE($D$6,K14,K15,K16) -> 0.025
C14: =Assumptions!C18 -> Base Case | D14: step1 | G14: 0.02 | H14: 0.02 | I14: 0.02 | J14: 0.025 | K14: 0.025
C15: =Assumptions!C19 -> Best Case | D15: inputs | G15: 0.018 | H15: 0.018 | I15: 0.018 | J15: 0.02 | K15: 0.02
C16: =Assumptions!C20 -> Worst Case | D16: blue | G16: 0.025 | H16: 0.025 | I16: 0.025 | J16: 0.025 | K16: 0.025
B21: SALES SCENARIOS
B23: Sales Price - $/Unit | G23: =CHOOSE($D$6,G25,G26,G27) -> 800 | H23: =CHOOSE($D$6,H25,H26,H27) -> 725 | I23: =CHOOSE($D$6,I25,I26,I27) -> 825 | J23: =CHOOSE($D$6,J25,J26,J27) -> 800 | K23: =CHOOSE($D$6,K25,K26,K27) -> 750
C25: =C14 -> Base Case | G25: 800 | H25: 725 | I25: 825 | J25: 800 | K25: 750
A26: =Assumptions!F19 -> 0.04 | C26: =C15 -> Best Case | G26: =G25*(1+$A26) -> 832 | H26: =H25*(1+$A26) -> 754 | I26: =I25*(1+$A26) -> 858 | J26: =J25*(1+$A26) -> 832 | K26: =K25*(1+$A26) -> 780
A27: =Assumptions!F20 -> -0.04 | C27: =C16 -> Worst Case | G27: =G25*(1+$A27) -> 768 | H27: =H25*(1+$A27) -> 696 | I27: =I25*(1+$A27) -> 792 | J27: =J25*(1+$A27) -> 768 | K27: =K25*(1+$A27) -> 720
B30: Sales Volume Growth | G30: =CHOOSE($D$6,G32,G33,G34) -> 0.05 | H30: =CHOOSE($D$6,H32,H33,H34) -> 0.04 | I30: =CHOOSE($D$6,I32,I33,I34) -> 0.04 | J30: =CHOOSE($D$6,J32,J33,J34) -> 0.04 | K30: =CHOOSE($D$6,K32,K33,K34) -> 0.04
C32: =C14 -> Base Case | G32: 0.05 | H32: 0.04 | I32: 0.04 | J32: 0.04 | K32: 0.04
C33: =C15 -> Best Case | G33: 0.05 | H33: 0.04 | I33: 0.05 | J33: 0.05 | K33: 0.04
C34: =C16 -> Worst Case | G34: 0.04 | H34: 0.04 | I34: 0.03 | J34: 0.03 | K34: 0.02

Sheet Model
O1: ="Currently Running : "&CHOOSE(Scenarios!$D$6,Scenarios!C14,Scenarios!C15,Scenarios!C16)&" Scenario" -> Currently Running : Base Case Scenario
B2: =Scenarios!B1 -> Blu Containers Company
B3: Revenue Schedule
H6: Historical data | K6: Projected
F7: Units | H7: =I7-1 -> 2020 | I7: =J7-1 -> 2021 | J7: =K7-1 -> 2022 | K7: =Scenarios!G6 -> 2023 | L7: =Scenarios!H6 -> 2024 | M7: =Scenarios!I6 -> 2025 | N7: =Scenarios!J6 -> 2026 | O7: =Scenarios!K6 -> 2027
B9: Pricing
C10: Gross Sales Price | F10: ($/unit) | J10: 694.4 | K10: =Scenarios!G23 -> 800 | L10: =Scenarios!H23 -> 725 | M10: =Scenarios!I23 -> 825 | N10: =Scenarios!J23 -> 800 | O10: =Scenarios!K23 -> 750
C11: Cost Inflation | F11: (%) | K11: =Scenarios!G12 -> 0.02 | L11: =Scenarios!H12 -> 0.02 | M11: =Scenarios!I12 -> 0.02 | N11: =Scenarios!J12 -> 0.025 | O11: =Scenarios!K12 -> 0.025
C12: Freight & Warehousing | F12: ($/unit) | J12: 100 | K12: =J12*(1+K11) -> 102 | L12: =K12*(1+L11) -> 104.04 | M12: =L12*(1+M11) -> 106.1208 | N12: =M12*(1+N11) -> 108.77382 | O12: =N12*(1+O11) -> 111.49317
C13: Net Sales Price | F13: ($/unit) | J13: =J10-J12 -> 594.4 | K13: =K10-K12 -> 698 | L13: =L10-L12 -> 620.96 | M13: =M10-M12 -> 718.8792 | N13: =N10-N12 -> 691.22618 | O13: =O10-O12 -> 638.50683
B16: Sales Volume
C17: Annual Factory Capacity | F17: (000's units) | K17: =Assumptions!N17 -> 420 | L17: =K17 -> 420 | M17: =L17 -> 420 | N17: =M17 -> 420 | O17: =N17 -> 420
C19: Sales Volume Growth | F19: (%) | K19: =Scenarios!G30 -> 0.05 | L19: =Scenarios!H30 -> 0.04 | M19: =Scenarios!I30 -> 0.04 | N19: =Scenarios!J30 -> 0.04 | O19: =Scenarios!K30 -> 0.04
C20: Annual Sales Volume | F20: (000's units) | J20: =J26*1000/J10 -> 344.47005 | K20: =MIN(J20*(K19+1),K17) -> 361.69355 | L20: =MIN(K20*(L19+1),L17) -> 376.16129 | M20: =MIN(L20*(M19+1),M17) -> 391.20774 | N20: =MIN(M20*(N19+1),N17) -> 406.85605 | O20: =MIN(N20*(O19+1),O17) -> 420
C22: Implied Operating Rate | K22: =K20/K17 -> 0.86117512 | L22: =L20/L17 -> 0.89562212 | M22: =M20/M17 -> 0.931447 | N22: =N20/N17 -> 0.96870488 | O22: =O20/O17 -> 1
B25: Revenue
C26: Gross Revenue | F26: ($ MM) | J26: =J83 -> 239.2 | K26: =(K10*K20)/1000 -> 289.35484 | L26: =(L10*L20)/1000 -> 272.71694 | M26: =(M10*M20)/1000 -> 322.74639 | N26: =(N10*N20)/1000 -> 325.48484 | O26: =(O10*O20)/1000 -> 315
C27: Freight & Warehousing | F27: ($ MM) | J27: =J84 -> 34.4 | K27: =(K12*K20)/1000 -> 36.892742 | L27: =(L12*L20)/1000 -> 39.135821 | M27: =(M12*M20)/1000 -> 41.515279 | N27: =(N12*N20)/1000 -> 44.255287 | O27: =(O12*O20)/1000 -> 46.82713
C28: Net Revenue | F28: ($ MM) | J28: =J26-J27 -> 204.8 | K28: =K26-K27 -> 252.4621 | L28: =L26-L27 -> 233.58111 | M28: =M26-M27 -> 281.23111 | N28: =N26-N27 -> 281.22955 | O28: =O26-O27 -> 268.17287
O31: =$O$1 -> Currently Running : Base Case Scenario
B32: =B$2 -> Blu Containers Company
B33: Costs of Production Schedule
K36: Projected
H37: =H$7 -> 2020 | I37: =I$7 -> 2021 | J37: =J$7 -> 2022 | K37: =K$7 -> 2023 | L37: =L$7 -> 2024 | M37: =M$7 -> 2025 | N37: =N$7 -> 2026 | O37: =O$7 -> 2027
B39: Annual Sales Volume | F39: (000's units) | J39: =J20 -> 344.47005 | K39: =K20 -> 361.69355 | L39: =L20 -> 376.16129 | M39: =M20 -> 391.20774 | N39: =N20 -> 406.85605 | O39: =O20 -> 420
B40: Cost Inflation | F40: (%) | L40: =L11 -> 0.02 | M40: =M11 -> 0.02 | N40: =N11 -> 0.025 | O40: =O11 -> 0.025
A42: 1 | B42: COSTS PER UNIT
C43: Variable Costs
D44: =Assumptions!C27 -> Raw Materials | F44: ($/unit) | K44: =Assumptions!E27 -> 226 | L44: =K44*(1+L40) -> 230.52 | M44: =L44*(1+M40) -> 235.1304 | N44: =M44*(1+N40) -> 241.00866 | O44: =N44*(1+O40) -> 247.03388
D45: =Assumptions!C28 -> Utilities | F45: ($/unit) | K45: =Assumptions!E28 -> 66.2 | L45: =K45*(1+L40) -> 67.524 | M45: =L45*(1+M40) -> 68.87448 | N45: =M45*(1+N40) -> 70.596342 | O45: =N45*(1+O40) -> 72.361251
D46: Total Variable Costs | F46: ($/unit) | K46: =K44+K45 -> 292.2 | L46: =L44+L45 -> 298.044 | M46: =M44+M45 -> 304.00488 | N46: =N44+N45 -> 311.605 | O46: =O44+O45 -> 319.39513
A48: 4 | C48: Fixed Costs
D49: =Assumptions!C29 -> Rent | F49: ($/unit) | K49: =K64*1000/K$39 -> 64.972129 | L49: =L64*1000/L$39 -> 63.722665 | M49: =M64*1000/M$39 -> 62.497229 | N49: =N64*1000/N$39 -> 61.595827 | O49: =O64*1000/O$39 -> 61.159883
D50: =Assumptions!C30 -> Operating Labour | F50: ($/unit) | K50: =K65*1000/K$39 -> 120.26756 | L50: =L65*1000/L$39 -> 117.95472 | M50: =M65*1000/M$39 -> 115.68636 | N50: =N65*1000/N$39 -> 114.01781 | O50: =O65*1000/O$39 -> 113.21085
D51: Other | F51: ($/unit) | K51: =K66*1000/K$39 -> 5.5295429 | L51: =L66*1000/L$39 -> 5.4232056 | M51: =M66*1000/M$39 -> 5.3189131 | N51: =N66*1000/N$39 -> 5.242198 | O51: =O66*1000/O$39 -> 5.2050964
D52: Total Fixed Costs | F52: ($/unit) | H52: OPERATING LEVERAGE | K52: =K49+K50+K51 -> 190.76923 | L52: =L49+L50+L51 -> 187.10059 | M52: =M49+M50+M51 -> 183.5025 | N52: =N49+N50+N51 -> 180.85583 | O52: =O49+O50+O51 -> 179.57583
C54: Total Costs | F54: ($/unit) | K54: =K52+K46 -> 482.96923 | L54: =L52+L46 -> 485.14459 | M54: =M52+M46 -> 487.50738 | N54: =N52+N46 -> 492.46083 | O54: =O52+O46 -> 498.97095
B57: COSTS IN MILLIONS
A58: 2 | C58: Variable Costs
D59: =D44 -> Raw Materials | F59: ($ MM) | K59: =(K44*K$39)/1000 -> 81.742742 | L59: =(L44*L$39)/1000 -> 86.712701 | M59: =(M44*M$39)/1000 -> 91.984833 | N59: =(N44*N$39)/1000 -> 98.055832 | O59: =(O44*O$39)/1000 -> 103.75423
D60: =D45 -> Utilities | F60: ($ MM) | K60: =(K45*K$39)/1000 -> 23.944113 | L60: =(L45*L$39)/1000 -> 25.399915 | M60: =(M45*M$39)/1000 -> 26.94423 | N60: =(N45*N$39)/1000 -> 28.722549 | O60: =(O45*O$39)/1000 -> 30.391725
D61: Total Variable Costs | F61: ($ MM) | K61: =K59+K60 -> 105.68685 | L61: =L59+L60 -> 112.11262 | M61: =M59+M60 -> 118.92906 | N61: =N59+N60 -> 126.77838 | O61: =O59+O60 -> 134.14595
A63: 3 | C63: Fixed Costs
D64: =D49 -> Rent | F64: ($ MM) | K64: =Assumptions!E29 -> 23.5 | L64: =K64*(1+L$40) -> 23.97 | M64: =L64*(1+M$40) -> 24.4494 | N64: =M64*(1+N$40) -> 25.060635 | O64: =N64*(1+O$40) -> 25.687151
D65: =D50 -> Operating Labour | F65: ($ MM) | K65: =Assumptions!E30 -> 43.5 | L65: =K65*(1+L$40) -> 44.37 | M65: =L65*(1+M$40) -> 45.2574 | N65: =M65*(1+N$40) -> 46.388835 | O65: =N65*(1+O$40) -> 47.548556
D66: =D51 -> Other | F66: ($ MM) | K66: =Assumptions!E31 -> 2 | L66: =K66*(1+L$40) -> 2.04 | M66: =L66*(1+M$40) -> 2.0808 | N66: =M66*(1+N$40) -> 2.13282 | O66: =N66*(1+O$40) -> 2.1861405
D67: Total Fixed Costs | F67: ($ MM) | K67: =K64+K65+K66 -> 69 | L67: =L64+L65+L66 -> 70.38 | M67: =M64+M65+M66 -> 71.7876 | N67: =N64+N65+N66 -> 73.58229 | O67: =O64+O65+O66 -> 75.421847
C69: Total Costs | F69: ($ MM) | K69: =K67+K61 -> 174.68685 | L69: =L67+L61 -> 182.49262 | M69: =M67+M61 -> 190.71666 | N69: =N67+N61 -> 200.36067 | O69: =O67+O61 -> 209.5678
O72: =$O$1 -> Currently Running : Base Case Scenario
B73: =B$2 -> Blu Containers Company
B74: Income Statement
B76: ($ Millions)
K77: Projected
H78: =H$7 -> 2020 | I78: =I$7 -> 2021 | J78: =J$7 -> 2022 | K78: =K$7 -> 2023 | L78: =L$7 -> 2024 | M78: =M$7 -> 2025 | N78: =N$7 -> 2026 | O78: =O$7 -> 2027
B80: Sales Volume | F80: (000's units) | J80: =J20 -> 344.47005
B82: Revenue
C83: Gross Revenue | H83: 244.8 | I83: 269.3 | J83: 239.2 | K83: =K26 -> 289.35484 | L83: =L26 -> 272.71694 | M83: =M26 -> 322.74639 | N83: =N26 -> 325.48484 | O83: =O26 -> 315
C84: Freight & Warehousing | H84: 31.3 | I84: 32.7 | J84: 34.4 | K84: =K27 -> 36.892742 | L84: =L27 -> 39.135821 | M84: =M27 -> 41.515279 | N84: =N27 -> 44.255287 | O84: =O27 -> 46.82713
C85: Net Revenue | H85: =+H83-H84 -> 213.5 | I85: =+I83-I84 -> 236.6 | J85: =+J83-J84 -> 204.8 | K85: =K28 -> 252.4621 | L85: =L28 -> 233.58111 | M85: =M28 -> 281.23111 | N85: =N28 -> 281.22955 | O85: =O28 -> 268.17287
C87: Cost of Sales | H87: 159.9 | I87: 164.6 | J87: 167.9 | K87: =K69 -> 174.68685 | L87: =L69 -> 182.49262 | M87: =M69 -> 190.71666 | N87: =N69 -> 200.36067 | O87: =O69 -> 209.5678
C88: S,G & A | H88: 3.4 | I88: 3.6 | J88: 3.8 | K88: =Assumptions!E32 -> 3.9 | L88: =K88*(1+L40) -> 3.978 | M88: =L88*(1+M40) -> 4.05756 | N88: =M88*(1+N40) -> 4.158999 | O88: =N88*(1+O40) -> 4.262974
C89: Total Costs | H89: =SUM(H87:H88) -> 163.3 | I89: =SUM(I87:I88) -> 168.2 | J89: =SUM(J87:J88) -> 171.7 | K89: =K87+K88 -> 178.58685 | L89: =L87+L88 -> 186.47062 | M89: =M87+M88 -> 194.77422 | N89: =N87+N88 -> 204.51967 | O89: =O87+O88 -> 213.83077
C91: Cost Adjustments - Gain/(Loss) | H91: 0 | I91: 0 | J91: 0 | K91: =Assumptions!J53 -> 0 | L91: =Assumptions!K53 -> 0 | M91: =Assumptions!L53 -> 0 | N91: =Assumptions!M53 -> 0 | O91: =Assumptions!N53 -> 0
C92: EBITDA | H92: =H85-H89+H91 -> 50.2 | I92: =I85-I89+I91 -> 68.4 | J92: =J85-J89+J91 -> 33.1 | K92: =K85-K89 -> 73.875242 | L92: =L85-L89 -> 47.110499 | M92: =M85-M89 -> 86.456886 | N92: =N85-N89 -> 76.709885 | O92: =O85-O89 -> 54.342096
C94: Depreciation | H94: 15.4 | I94: 15.5 | J94: 15.8 | K94: =K214 -> 16.174667 | L94: =L214 -> 16.724667 | M94: =M214 -> 17.296333 | N94: =N214 -> 17.876333 | O94: =O214 -> 18.468
C95: EBIT | H95: =H92-H94 -> 34.8 | I95: =I92-I94 -> 52.9 | J95: =J92-J94 -> 17.3 | K95: =K92-K94 -> 57.700575 | L95: =L92-L94 -> 30.385833 | M95: =M92-M94 -> 69.160553 | N95: =N92-N94 -> 58.833551 | O95: =O92-O94 -> 35.874096
C97: Interest Expense | H97: 15 | I97: 15 | J97: 14 | K97: =K326 -> 12 | L97: =L326 -> 10.564621 | M97: =M326 -> 9.4646151 | N97: =N326 -> 7.5737373 | O97: =O326 -> 6
C98: EBT | H98: =H95-H97 -> 19.8 | I98: =I95-I97 -> 37.9 | J98: =J95-J97 -> 3.3 | K98: =K95-K97 -> 45.700575 | L98: =L95-L97 -> 19.821212 | M98: =M95-M97 -> 59.695937 | N98: =N95-N97 -> 51.259814 | O98: =O95-O97 -> 29.874096
C100: Current Income Taxes | H100: 3 | I100: 8 | J100: 0 | K100: =K237 -> 14.245201 | L100: =L237 -> 5.187424 | M100: =M237 -> 19.143578 | N100: =N237 -> 16.190935 | O100: =O237 -> 8.7059336
C101: Deferred Income Taxes | H101: 2.7 | I101: 6.2 | J101: 1.1 | K101: =K238 -> 1.75 | L101: =L238 -> 1.75 | M101: =M238 -> 1.75 | N101: =N238 -> 1.75 | O101: =O238 -> 1.75
C102: Total Income Taxes | H102: =SUM(H100:H101) -> 5.7 | I102: =SUM(I100:I101) -> 14.2 | J102: =SUM(J100:J101) -> 1.1 | K102: =K239 -> 15.995201 | L102: =L239 -> 6.937424 | M102: =M239 -> 20.893578 | N102: =N239 -> 17.940935 | O102: =O239 -> 10.455934
C104: Net Income | H104: =H98-H102 -> 14.1 | I104: =I98-I102 -> 23.7 | J104: =J98-J102 -> 2.2 | K104: =K98-K102 -> 29.705374 | L104: =L98-L102 -> 12.883787 | M104: =M98-M102 -> 38.802359 | N104: =N98-N102 -> 33.318879 | O104: =O98-O102 -> 19.418162
B107: Margins
C108: EBITDA Margin | H108: =H92/H85 -> 0.23512881 | I108: =I92/I85 -> 0.28909552 | J108: =J92/J85 -> 0.16162109 | K108: =K92/K85 -> 0.29261914 | L108: =L92/L85 -> 0.20168796 | M108: =M92/M85 -> 0.30742291 | N108: =N92/N85 -> 0.27276609 | O108: =O92/O85 -> 0.2026383
C109: EBIT Margin | H109: =H95/H85 -> 0.16299766 | I109: =I95/I85 -> 0.22358411 | J109: =J95/J85 -> 0.084472656 | K109: =K95/K85 -> 0.22855144 | L109: =L95/L85 -> 0.13008685 | M109: =M95/M85 -> 0.24592071 | N109: =N95/N85 -> 0.20920117 | O109: =O95/O85 -> 0.13377228
C110: Return on Equity | J110: =J104/J184 -> 0.0085106383 | K110: =K104/K184 -> 0.10523957 | L110: =L104/L184 -> 0.044036398 | M110: =M104/M184 -> 0.11990351 | N110: =N104/N184 -> 0.095123873 | O110: =O104/O184 -> 0.053083683
O113: =$O$1 -> Currently Running : Base Case Scenario
B114: =B$2 -> Blu Containers Company
B115: Cash Flow Statement
B117: ($ Millions)
K118: Projected
H119: =H$7 -> 2020 | I119: =I$7 -> 2021 | J119: =J$7 -> 2022 | K119: =K$7 -> 2023 | L119: =L$7 -> 2024 | M119: =M$7 -> 2025 | N119: =N$7 -> 2026 | O119: =O$7 -> 2027
B120: Operating Activities
C121: Net Income | H121: 14.1 | I121: 23.7 | J121: 2.2 | K121: =K104 -> 29.705374 | L121: =L104 -> 12.883787 | M121: =M104 -> 38.802359 | N121: =N104 -> 33.318879 | O121: =O104 -> 19.418162
C122: Depreciation & Amortization | H122: 15.4 | I122: 15.5 | J122: 15.8 | K122: =K94 -> 16.174667 | L122: =L94 -> 16.724667 | M122: =M94 -> 17.296333 | N122: =N94 -> 17.876333 | O122: =O94 -> 18.468
C123: Deferred Income Taxes | H123: 2.7 | I123: 6.2 | J123: 1.1 | K123: =K101 -> 1.75 | L123: =L101 -> 1.75 | M123: =M101 -> 1.75 | N123: =N101 -> 1.75 | O123: =O101 -> 1.75
C124: Changes in working capital | H124: 0 | I124: 0 | J124: 0 | K124: =K275 -> -2.0659834 | L124: =L275 -> 6.5517359 | M124: =M275 -> -1.2735904 | N124: =N275 -> -1.1359731 | O124: =O275 -> 3.2169857
C125: Operating Cash Flow | H125: =SUM(H121:H124) -> 32.2 | I125: =SUM(I121:I124) -> 45.4 | J125: =SUM(J121:J124) -> 19.1 | K125: =SUM(K121:K124) -> 45.564057 | L125: =SUM(L121:L124) -> 37.91019 | M125: =SUM(M121:M124) -> 56.575102 | N125: =SUM(N121:N124) -> 51.809239 | O125: =SUM(O121:O124) -> 42.853148
B128: Investing Activities
C129: CAPEX | H129: -14.1 | I129: -15 | J129: -15.5 | K129: =-Assumptions!J58 -> -16 | L129: =-Assumptions!K58 -> -17 | M129: =-Assumptions!L58 -> -17.3 | N129: =-Assumptions!M58 -> -17.5 | O129: =-Assumptions!N58 -> -18
C130: Other | H130: -5 | I130: 4 | J130: 3 | K130: =Assumptions!J56 -> 0 | L130: =Assumptions!K56 -> 0 | M130: =Assumptions!L56 -> 0 | N130: =Assumptions!M56 -> 0 | O130: =Assumptions!N56 -> 0
C131: Investing Cash Flow | H131: =SUM(H129:H130) -> -19.1 | I131: =SUM(I129:I130) -> -11 | J131: =SUM(J129:J130) -> -12.5 | K131: =SUM(K129:K130) -> -16 | L131: =SUM(L129:L130) -> -17 | M131: =SUM(M129:M130) -> -17.3 | N131: =SUM(N129:N130) -> -17.5 | O131: =SUM(O129:O130) -> -18
B134: Financing Activities
C135: Revolver Issuance / (Repayment) | H135: 0 | I135: 0 | J135: 0 | K135: =K306 -> 1.0770176 | L135: =L306 -> 6.6665675 | M135: =M306 -> -6.5146305 | N135: =N306 -> -1.2289546 | O135: =O306 -> 2.6139756
C136: Term Debt Issuance / (Repayment) | H136: -25 | I136: -25 | J136: -25 | K136: =K318 -> -25 | L136: =L318 -> -25 | M136: =M318 -> -25 | N136: =N318 -> -25 | O136: =O318 -> -25
C137: Common Shares Issuance/ (Buy-Back) | H137: 0 | I137: 0 | J137: 0 | K137: =K339 -> 0 | L137: =L339 -> 0 | M137: =M339 -> 0 | N137: =N339 -> 0 | O137: =O339 -> 0
C138: Common Dividends | H138: -2.8 | I138: -4.7 | J138: -2.4 | K138: =-K344 -> -5.9410748 | L138: =-L344 -> -2.5767575 | M138: =-M344 -> -7.7604719 | N138: =-N344 -> -6.6637758 | O138: =-O344 -> -3.8836325
C139: Financing Cash Flow | H139: =SUM(H135:H138) -> -27.8 | I139: =SUM(I135:I138) -> -29.7 | J139: =SUM(J135:J138) -> -27.4 | K139: =SUM(K135:K138) -> -29.864057 | L139: =SUM(L135:L138) -> -20.91019 | M139: =SUM(M135:M138) -> -39.275102 | N139: =SUM(N135:N138) -> -32.89273 | O139: =SUM(O135:O138) -> -26.269657
B142: Change in the Cash Position | H142: =H139+H131+H125 -> -14.7 | I142: =I139+I131+I125 -> 4.7 | J142: =J139+J131+J125 -> -20.8 | K142: =K139+K131+K125 -> -0.3 | L142: =L139+L131+L125 -> 0 | M142: =M139+M131+M125 -> 0 | N142: =N139+N131+N125 -> 1.4165089 | O142: =O139+O131+O125 -> -1.4165089
B143: Beginning Cash | H143: 31.1 | I143: =+H144 -> 16.4 | J143: =+I144 -> 21.1 | K143: =+J144 -> 0.3 | L143: =+K144 -> 7.1054274e-15 | M143: =+L144 -> 7.1054274e-15 | N143: =+M144 -> 7.1054274e-15 | O143: =+N144 -> 1.4165089
...

Sheet Model (2)
O1: ="Currently Running : "&CHOOSE(Scenarios!$D$6,Scenarios!C14,Scenarios!C15,Scenarios!C16)&" Scenario" -> Currently Running : Base Case Scenario
B2: =Scenarios!B1 -> Blu Containers Company
B3: Revenue Schedule
H6: Historical data | K6: Projected
F7: Units | H7: =I7-1 -> 2020 | I7: =J7-1 -> 2021 | J7: =K7-1 -> 2022 | K7: =Scenarios!G6 -> 2023 | L7: =Scenarios!H6 -> 2024 | M7: =Scenarios!I6 -> 2025 | N7: =Scenarios!J6 -> 2026 | O7: =Scenarios!K6 -> 2027
B9: Pricing
C10: Gross Sales Price | F10: ($/unit) | J10: 694.4 | K10: =Scenarios!G23 -> 800 | L10: =Scenarios!H23 -> 725 | M10: =Scenarios!I23 -> 825 | N10: =Scenarios!J23 -> 800 | O10: =Scenarios!K23 -> 750
C11: Cost Inflation | F11: (%) | K11: =Scenarios!G12 -> 0.02 | L11: =Scenarios!H12 -> 0.02 | M11: =Scenarios!I12 -> 0.02 | N11: =Scenarios!J12 -> 0.025 | O11: =Scenarios!K12 -> 0.025
C12: Freight & Warehousing | F12: ($/unit) | J12: 100 | K12: =J12*(1+K11) -> 102 | L12: =K12*(1+L11) -> 104.04 | M12: =L12*(1+M11) -> 106.1208 | N12: =M12*(1+N11) -> 108.77382 | O12: =N12*(1+O11) -> 111.49317
C13: Net Sales Price | F13: ($/unit) | J13: =J10-J12 -> 594.4 | K13: =K10-K12 -> 698 | L13: =L10-L12 -> 620.96 | M13: =M10-M12 -> 718.8792 | N13: =N10-N12 -> 691.22618 | O13: =O10-O12 -> 638.50683
B16: Sales Volume
C17: Annual Factory Capacity | F17: (000's units) | K17: =Assumptions!N17 -> 420 | L17: =K17 -> 420 | M17: =L17 -> 420 | N17: =M17 -> 420 | O17: =N17 -> 420
C19: Sales Volume Growth | F19: (%) | K19: =Scenarios!G30 -> 0.05 | L19: =Scenarios!H30 -> 0.04 | M19: =Scenarios!I30 -> 0.04 | N19: =Scenarios!J30 -> 0.04 | O19: =Scenarios!K30 -> 0.04
C20: Annual Sales Volume | F20: (000's units) | J20: =J26*1000/J10 -> 344.47005 | K20: =MIN(J20*(K19+1),K17) -> 361.69355 | L20: =MIN(K20*(L19+1),L17) -> 376.16129 | M20: =MIN(L20*(M19+1),M17) -> 391.20774 | N20: =MIN(M20*(N19+1),N17) -> 406.85605 | O20: =MIN(N20*(O19+1),O17) -> 420
C22: Implied Operating Rate | K22: =K20/K17 -> 0.86117512 | L22: =L20/L17 -> 0.89562212 | M22: =M20/M17 -> 0.931447 | N22: =N20/N17 -> 0.96870488 | O22: =O20/O17 -> 1
B25: Revenue
C26: Gross Revenue | F26: ($ MM) | J26: =J83 -> 239.2 | K26: =(K10*K20)/1000 -> 289.35484 | L26: =(L10*L20)/1000 -> 272.71694 | M26: =(M10*M20)/1000 -> 322.74639 | N26: =(N10*N20)/1000 -> 325.48484 | O26: =(O10*O20)/1000 -> 315
C27: Freight & Warehousing | F27: ($ MM) | J27: =J84 -> 34.4 | K27: =(K12*K20)/1000 -> 36.892742 | L27: =(L12*L20)/1000 -> 39.135821 | M27: =(M12*M20)/1000 -> 41.515279 | N27: =(N12*N20)/1000 -> 44.255287 | O27: =(O12*O20)/1000 -> 46.82713
C28: Net Revenue | F28: ($ MM) | J28: =J26-J27 -> 204.8 | K28: =K26-K27 -> 252.4621 | L28: =L26-L27 -> 233.58111 | M28: =M26-M27 -> 281.23111 | N28: =N26-N27 -> 281.22955 | O28: =O26-O27 -> 268.17287
O31: =$O$1 -> Currently Running : Base Case Scenario
B32: =B$2 -> Blu Containers Company
B33: Costs of Production Schedule
K36: Projected
H37: =H$7 -> 2020 | I37: =I$7 -> 2021 | J37: =J$7 -> 2022 | K37: =K$7 -> 2023 | L37: =L$7 -> 2024 | M37: =M$7 -> 2025 | N37: =N$7 -> 2026 | O37: =O$7 -> 2027
B39: Annual Sales Volume | F39: (000's units) | J39: =J20 -> 344.47005 | K39: =K20 -> 361.69355 | L39: =L20 -> 376.16129 | M39: =M20 -> 391.20774 | N39: =N20 -> 406.85605 | O39: =O20 -> 420
B40: Cost Inflation | F40: (%) | L40: =L11 -> 0.02 | M40: =M11 -> 0.02 | N40: =N11 -> 0.025 | O40: =O11 -> 0.025
A42: 1 | B42: COSTS PER UNIT
C43: Variable Costs
D44: =Assumptions!C27 -> Raw Materials | F44: ($/unit) | K44: =Assumptions!E27 -> 226 | L44: =K44*(1+L40) -> 230.52 | M44: =L44*(1+M40) -> 235.1304 | N44: =M44*(1+N40) -> 241.00866 | O44: =N44*(1+O40) -> 247.03388
D45: =Assumptions!C28 -> Utilities | F45: ($/unit) | K45: =Assumptions!E28 -> 66.2 | L45: =K45*(1+L40) -> 67.524 | M45: =L45*(1+M40) -> 68.87448 | N45: =M45*(1+N40) -> 70.596342 | O45: =N45*(1+O40) -> 72.361251
D46: Total Variable Costs | F46: ($/unit) | K46: =K44+K45 -> 292.2 | L46: =L44+L45 -> 298.044 | M46: =M44+M45 -> 304.00488 | N46: =N44+N45 -> 311.605 | O46: =O44+O45 -> 319.39513
A48: 4 | C48: Fixed Costs
D49: =Assumptions!C29 -> Rent | F49: ($/unit) | K49: =K64*1000/K$39 -> 64.972129 | L49: =L64*1000/L$39 -> 63.722665 | M49: =M64*1000/M$39 -> 62.497229 | N49: =N64*1000/N$39 -> 61.595827 | O49: =O64*1000/O$39 -> 61.159883
D50: =Assumptions!C30 -> Operating Labour | F50: ($/unit) | K50: =K65*1000/K$39 -> 120.26756 | L50: =L65*1000/L$39 -> 117.95472 | M50: =M65*1000/M$39 -> 115.68636 | N50: =N65*1000/N$39 -> 114.01781 | O50: =O65*1000/O$39 -> 113.21085
D51: Other | F51: ($/unit) | K51: =K66*1000/K$39 -> 5.5295429 | L51: =L66*1000/L$39 -> 5.4232056 | M51: =M66*1000/M$39 -> 5.3189131 | N51: =N66*1000/N$39 -> 5.242198 | O51: =O66*1000/O$39 -> 5.2050964
D52: Total Fixed Costs | F52: ($/unit) | H52: OPERATING LEVERAGE | K52: =K49+K50+K51 -> 190.76923 | L52: =L49+L50+L51 -> 187.10059 | M52: =M49+M50+M51 -> 183.5025 | N52: =N49+N50+N51 -> 180.85583 | O52: =O49+O50+O51 -> 179.57583
C54: Total Costs | F54: ($/unit) | K54: =K52+K46 -> 482.96923 | L54: =L52+L46 -> 485.14459 | M54: =M52+M46 -> 487.50738 | N54: =N52+N46 -> 492.46083 | O54: =O52+O46 -> 498.97095
B57: COSTS IN MILLIONS
A58: 2 | C58: Variable Costs
D59: =D44 -> Raw Materials | F59: ($ MM) | K59: =(K44*K$39)/1000 -> 81.742742 | L59: =(L44*L$39)/1000 -> 86.712701 | M59: =(M44*M$39)/1000 -> 91.984833 | N59: =(N44*N$39)/1000 -> 98.055832 | O59: =(O44*O$39)/1000 -> 103.75423
D60: =D45 -> Utilities | F60: ($ MM) | K60: =(K45*K$39)/1000 -> 23.944113 | L60: =(L45*L$39)/1000 -> 25.399915 | M60: =(M45*M$39)/1000 -> 26.94423 | N60: =(N45*N$39)/1000 -> 28.722549 | O60: =(O45*O$39)/1000 -> 30.391725
D61: Total Variable Costs | F61: ($ MM) | K61: =K59+K60 -> 105.68685 | L61: =L59+L60 -> 112.11262 | M61: =M59+M60 -> 118.92906 | N61: =N59+N60 -> 126.77838 | O61: =O59+O60 -> 134.14595
A63: 3 | C63: Fixed Costs
D64: =D49 -> Rent | F64: ($ MM) | K64: =Assumptions!E29 -> 23.5 | L64: =K64*(1+L$40) -> 23.97 | M64: =L64*(1+M$40) -> 24.4494 | N64: =M64*(1+N$40) -> 25.060635 | O64: =N64*(1+O$40) -> 25.687151
D65: =D50 -> Operating Labour | F65: ($ MM) | K65: =Assumptions!E30 -> 43.5 | L65: =K65*(1+L$40) -> 44.37 | M65: =L65*(1+M$40) -> 45.2574 | N65: =M65*(1+N$40) -> 46.388835 | O65: =N65*(1+O$40) -> 47.548556
D66: =D51 -> Other | F66: ($ MM) | K66: =Assumptions!E31 -> 2 | L66: =K66*(1+L$40) -> 2.04 | M66: =L66*(1+M$40) -> 2.0808 | N66: =M66*(1+N$40) -> 2.13282 | O66: =N66*(1+O$40) -> 2.1861405
D67: Total Fixed Costs | F67: ($ MM) | K67: =K64+K65+K66 -> 69 | L67: =L64+L65+L66 -> 70.38 | M67: =M64+M65+M66 -> 71.7876 | N67: =N64+N65+N66 -> 73.58229 | O67: =O64+O65+O66 -> 75.421847
C69: Total Costs | F69: ($ MM) | K69: =K67+K61 -> 174.68685 | L69: =L67+L61 -> 182.49262 | M69: =M67+M61 -> 190.71666 | N69: =N67+N61 -> 200.36067 | O69: =O67+O61 -> 209.5678
O72: =$O$1 -> Currently Running : Base Case Scenario
B73: =B$2 -> Blu Containers Company
B74: Income Statement
B76: ($ Millions)
K77: Projected
H78: =H$7 -> 2020 | I78: =I$7 -> 2021 | J78: =J$7 -> 2022 | K78: =K$7 -> 2023 | L78: =L$7 -> 2024 | M78: =M$7 -> 2025 | N78: =N$7 -> 2026 | O78: =O$7 -> 2027
B80: Sales Volume | F80: (000's units) | J80: =J20 -> 344.47005
B82: Revenue
C83: Gross Revenue | H83: 244.8 | I83: 269.3 | J83: 239.2 | K83: =K26 -> 289.35484 | L83: =L26 -> 272.71694 | M83: =M26 -> 322.74639 | N83: =N26 -> 325.48484 | O83: =O26 -> 315
C84: Freight & Warehousing | H84: 31.3 | I84: 32.7 | J84: 34.4 | K84: =K27 -> 36.892742 | L84: =L27 -> 39.135821 | M84: =M27 -> 41.515279 | N84: =N27 -> 44.255287 | O84: =O27 -> 46.82713
C85: Net Revenue | H85: =+H83-H84 -> 213.5 | I85: =+I83-I84 -> 236.6 | J85: =+J83-J84 -> 204.8 | K85: =K28 -> 252.4621 | L85: =L28 -> 233.58111 | M85: =M28 -> 281.23111 | N85: =N28 -> 281.22955 | O85: =O28 -> 268.17287
C87: Cost of Sales | H87: 159.9 | I87: 164.6 | J87: 167.9 | K87: =K69 -> 174.68685 | L87: =L69 -> 182.49262 | M87: =M69 -> 190.71666 | N87: =N69 -> 200.36067 | O87: =O69 -> 209.5678
C88: S,G & A | H88: 3.4 | I88: 3.6 | J88: 3.8 | K88: =Assumptions!E32 -> 3.9 | L88: =K88*(1+L40) -> 3.978 | M88: =L88*(1+M40) -> 4.05756 | N88: =M88*(1+N40) -> 4.158999 | O88: =N88*(1+O40) -> 4.262974
C89: Total Costs | H89: =SUM(H87:H88) -> 163.3 | I89: =SUM(I87:I88) -> 168.2 | J89: =SUM(J87:J88) -> 171.7 | K89: =K87+K88 -> 178.58685 | L89: =L87+L88 -> 186.47062 | M89: =M87+M88 -> 194.77422 | N89: =N87+N88 -> 204.51967 | O89: =O87+O88 -> 213.83077
C91: Cost Adjustments - Gain/(Loss) | H91: 0 | I91: 0 | J91: 0 | K91: =Assumptions!J53 -> 0 | L91: =Assumptions!K53 -> 0 | M91: =Assumptions!L53 -> 0 | N91: =Assumptions!M53 -> 0 | O91: =Assumptions!N53 -> 0
C92: EBITDA | H92: =H85-H89+H91 -> 50.2 | I92: =I85-I89+I91 -> 68.4 | J92: =J85-J89+J91 -> 33.1 | K92: =K85-K89 -> 73.875242 | L92: =L85-L89 -> 47.110499 | M92: =M85-M89 -> 86.456886 | N92: =N85-N89 -> 76.709885 | O92: =O85-O89 -> 54.342096
C94: Depreciation | H94: 15.4 | I94: 15.5 | J94: 15.8
C95: EBIT | H95: =H92-H94 -> 34.8 | I95: =I92-I94 -> 52.9 | J95: =J92-J94 -> 17.3
C97: Interest Expense | H97: 15 | I97: 15 | J97: 14
C98: EBT | H98: =H95-H97 -> 19.8 | I98: =I95-I97 -> 37.9 | J98: =J95-J97 -> 3.3
C100: Current Income Taxes | H100: 3 | I100: 8 | J100: 0
C101: Deferred Income Taxes | H101: 2.7 | I101: 6.2 | J101: 1.1
C102: Total Income Taxes | H102: =SUM(H100:H101) -> 5.7 | I102: =SUM(I100:I101) -> 14.2 | J102: =SUM(J100:J101) -> 1.1
C104: Net Income | H104: =H98-H102 -> 14.1 | I104: =I98-I102 -> 23.7 | J104: =J98-J102 -> 2.2
B107: Margins
C108: EBITDA Margin | H108: =H92/H85 -> 0.23512881 | I108: =I92/I85 -> 0.28909552 | J108: =J92/J85 -> 0.16162109
C109: EBIT Margin | H109: =H95/H85 -> 0.16299766 | I109: =I95/I85 -> 0.22358411 | J109: =J95/J85 -> 0.084472656
C110: Return on Equity | J110: =J104/J184 -> 0.0085106383
O113: =$O$1 -> Currently Running : Base Case Scenario
B114: =B$2 -> Blu Containers Company
B115: Cash Flow Statement
B117: ($ Millions)
K118: Projected
H119: =H$7 -> 2020 | I119: =I$7 -> 2021 | J119: =J$7 -> 2022 | K119: =K$7 -> 2023 | L119: =L$7 -> 2024 | M119: =M$7 -> 2025 | N119: =N$7 -> 2026 | O119: =O$7 -> 2027
B120: Operating Activities | F120: unwinding the accruals on the inc stmt
C121: Net Income | H121: 14.1 | I121: 23.7 | J121: 2.2
C122: Depreciation & Amortization | H122: 15.4 | I122: 15.5 | J122: 15.8
C123: Deferred Income Taxes | H123: 2.7 | I123: 6.2 | J123: 1.1
C124: Changes in working capital | H124: 0 | I124: 0 | J124: 0
C125: Operating Cash Flow | H125: =SUM(H121:H124) -> 32.2 | I125: =SUM(I121:I124) -> 45.4 | J125: =SUM(J121:J124) -> 19.1
B128: Investing Activities | F128: reflect changes in the asset on the BS that were not included in Inc STMT
C129: CAPEX | H129: -14.1 | I129: -15 | J129: -15.5 | K129: =-Assumptions!J58 -> -16 | L129: =-Assumptions!K58 -> -17 | M129: =-Assumptions!L58 -> -17.3 | N129: =-Assumptions!M58 -> -17.5 | O129: =-Assumptions!N58 -> -18
C130: Other | H130: -5 | I130: 4 | J130: 3
C131: Investing Cash Flow | H131: =SUM(H129:H130) -> -19.1 | I131: =SUM(I129:I130) -> -11 | J131: =SUM(J129:J130) -> -12.5
B134: Financing Activities | F134: Changes in LIABILITIES AND EQUITY ON THE BS NOT INCLUDED IN INC STMT | P134: all the ROWS COME FROM THE CHANGE ROWS
C135: Revolver Issuance / (Repayment) | H135: 0 | I135: 0 | J135: 0
C136: Term Debt Issuance / (Repayment) | H136: -25 | I136: -25 | J136: -25
C137: Common Shares Issuance/ (Buy-Back) | H137: 0 | I137: 0 | J137: 0
C138: Common Dividends | H138: -2.8 | I138: -4.7 | J138: -2.4
C139: Financing Cash Flow | H139: =SUM(H135:H138) -> -27.8 | I139: =SUM(I135:I138) -> -29.7 | J139: =SUM(J135:J138) -> -27.4
B142: Change in the Cash Position | F142: CFO+CFI+CFF | H142: =H139+H131+H125 -> -14.7 | I142: =I139+I131+I125 -> 4.7 | J142: =J139+J131+J125 -> -20.8
B143: Beginning Cash | F143: END OF PREVIOUS | H143: 31.1 | I143: =+H144 -> 16.4 | J143: =+I144 -> 21.1
...

Sheet Sheet1
D12: Custom formating
D13: click on customised tab , the number is still a number and can be used in calculation
E14: 4.5
E15: 25
D16: to format cell to pos, neg, zero, text
E17: 65
E18: -65
E19: 0
E20: fjjgk
D21: Backing into fixed and variable
D22: you might just know that last year variable costs were 75% of the total
G23: 2022A | H23: 2023
F24: Price - $/unit | G24: 800 | H24: 800
F25: unit growth | H25: 0.03
F26: Units (000s) | G26: =G27*1000/G24 -> 125 | H26: =G26*(1+H25) -> 128.75
F27: Revenue - $MM | G27: 100 | H27: =H24*H26/1000 -> 103
F28: Revenue frowth
F29: Inflation | H29: 0.025
F30: Variable cost % | G30: 0.75
F31: Fixed cost % | G31: =1-G30 -> 0.25
F33: Variable cost - $/unit | G33: =G37*1000/G26 -> 360 | H33: =G33*(1+H29) -> 369 | I33: 1
F34: Fixed cost - $/unit | G34: =G38*1000/G26 -> 120 | H34: =H38*1000/H26 -> 119.41748 | I34: 4
F35: total cost - $/unit | G35: =G33+G34 -> 480 | H35: =H33+H34 -> 488.41748
F37: Variable cost - $MM | G37: =G30*G41 -> 45 | H37: =H33*H26/1000 -> 47.50875 | I37: 2
F38: Fixed cost - $MM | G38: =G31*G41 -> 15 | H38: =G38*(1+H29) -> 15.375 | I38: 3
F39: total cost - $MM | G39: =G37+G38 -> 60 | H39: =H37+H38 -> 62.88375
F41: operating costs | G41: 60 | H41: =H39 -> 62.88375
F42: gross profit | G42: 40 | H42: =H27-H41 -> 40.11625
F43: profit increase | H43: =H42/G42-1 -> 0.00290625
F45: profit margin | G45: =G42/G27 -> 0.4 | H45: =H42/H27 -> 0.38947816
D47: Capturing the operating leverage
D48: how do we know if a company is experiencing operating leverage
G50: 2022A | H50: 2023
F51: Annual growth | H51: =H52/G52-1 -> 0.05
F52: Revenue | G52: 100 | H52: 105
F54: Operating costs | G54: 60 | H54: 63
F55: Gross profit | G55: =G52-G54 -> 40 | H55: =H52-H54 -> 42
F57: profit margin | G57: =G55/G52 -> 0.4 | H57: =H55/H52 -> 0.4
D59: if you forecast the ,argin and keep it constant; what does that assume about the costs ?
D60: this assumes that ALL the costs at the company are variable
D61: all comanises have some fixed costs
D62: what exactly is operating leverage?
D63: the idea that as revenue increases, the profit increases even faster because the company has fixed costs
D64: to check if there is operating leverage we need to check for the fixed cost per unit
D65: fixed cost per unit are going down because we are splitting fixed costs on more units
D66: WHEN MARGIN GOES UP THERE WOULD BE MORE PROFIT
D69: Semi variable costs
D70: act like fixed costs within a range of sales vou,e
D71: example : operating labour, you have 100 people up to 150 000 units
D72: at that level you can run two shifts
... D74: for every additional 25 000 units you need another shift, and 50 more people
G76: 2022A | H76: 2023F | J76: Units | K76: Cost
F77: Units (000s) | G77: 120 | H77: 120 | J77: 0 | K77: 10
F78: Max of SV (000s) | H78: 150 | J78: 151 | K78: 15
J79: 176 | K79: 20
J80: 201 | K80: 25
F81: Inflation | H81: 0.028
F83: Variable - $/unit | G83: 395 | H83: =G83*(1+H81) -> 406.06
F84: Variable - $MM | G84: 47 | H84: =H83*H77/1000 -> 48.7272
F86: SV LABOUR - $/unit | G86: 83
F87: SV LABOUR - $MM | G87: 10 | H87: =VLOOKUP(H77,J77:K80,2,TRUE) -> 10 | I87: the method of calculation of others variables would work here only if we were to sell lower than the max of 150
F89: FIXED - $/unit | G89: =G90*1000/G77 -> 125 | H89: =H90*1000/H77 -> 128.5
F90: FIXED - $MM | G90: 15 | H90: =G90*(1+H81) -> 15.42
D93: TAX CALCULATION
G94: 2023F
G95: EBT | H95: RATE | I95: TAX
D96: EBT (Accounting) | G96: 100 | H96: 0.35 | I96: =G96*H96 -> 35
D97: Taxable income (Gov'T) | G97: 30 | H97: 0.35 | I97: =G97*H97 -> 10.5 | J97: company hopes this number is lower than EBT (for example if the government depreciation is high)
D100: INCOME STATEMENT | G100: 2023F
D101: Current Tax/cash | G101: =I97 -> 10.5
D102: Deferred Tax | G102: =G103-G101 -> 24.5 | H102: NON CASH
D103: Total Tax | G103: =I96 -> 35
D105: Net income | G105: =G96-G103 -> 65
D107: Cash flow statement
D108: Net income | G108: =G105 -> 65
D109: Deferred Tax | G109: =G102 -> 24.5 | H109: SAME ON CFLO STMT
D112: Balance sheet | F112: 2022A | G112: 2023F
D113: Def tax liability | F113: 10 | G113: =F113+G109 -> 34.5 | H113: deferred tax liability must beCUMULATIVE
D115: AUTOMATING THE DAYS PER YEAR
F116: 2022 | G116: 2023 | H116: 2024 | I116: 2025
D117: DAYS PER YEAR | G117: =DATE(G116,12,31)-DATE(F116,12,31) -> 365 | H117: =DATE(H116,12,31)-DATE(G116,12,31) -> 366 | I117: =DATE(I116,12,31)-DATE(H116,12,31) -> 365
D120: 44926
D123: to find hard value => F5 g to special => select constants => model goes to all constants in the file shaded in grey
D124: to find errored formulas => select whole row => Ctrl +/
D126: USE SPARKLINE IN SUMMARY FOR VISUALISATION
D129: three ways to automate summary !
D130: VBA copy paste macro with a button saying run the copy paste macro, it willgo to the scenario page, run the live model and copy the value directly to the table correspondent
D131: use data table (1 variable data table)
D132: self referencing if statementr

Sheet Scenarios (2)
B1: =Assumptions!B1 -> Blu Containers Company
B2: Economic and Sales Scenarios
B6: SCENARIO SWITCH: | D6: 2 | G6: =Assumptions!G8 -> 2023 | H6: =G6+1 -> 2024 | I6: =H6+1 -> 2025 | J6: =I6+1 -> 2026 | K6: =J6+1 -> 2027
D9: Base Case
B10: ECONOMIC SCENARIOS
B12: Cost Inflation | D12: LIVE CASE -> | G12: =CHOOSE($D$6,G14,G15,G16) -> 0.018 | H12: =CHOOSE(MATCH($D$9,$C$14:$C$16,0),H14,H15,H16) -> 0.02 | I12: =INDEX(I14:I16,$D$6) -> 0.018 | J12: =INDEX(J14:J16,$D$6) -> 0.02 | K12: =INDEX(K14:K16,$D$6) -> 0.02
C14: =Assumptions!C18 -> Base Case | D14: step1 | G14: 0.02 | H14: 0.02 | I14: 0.02 | J14: 0.025 | K14: 0.025
C15: =Assumptions!C19 -> Best Case | D15: inputs | G15: 0.018 | H15: 0.018 | I15: 0.018 | J15: 0.02 | K15: 0.02
C16: =Assumptions!C20 -> Worst Case | D16: blue | G16: 0.025 | H16: 0.025 | I16: 0.025 | J16: 0.025 | K16: 0.025
B21: SALES SCENARIOS
B23: Sales Price - $/Unit | D23: 1 | G23: =CHOOSE($D$23,G25,G26,G27) -> 800 | H23: =CHOOSE($D$23,H25,H26,H27) -> 725 | I23: =CHOOSE($D$23,I25,I26,I27) -> 825 | J23: =CHOOSE($D$23,J25,J26,J27) -> 800 | K23: =CHOOSE($D$23,K25,K26,K27) -> 750
C25: =C14 -> Base Case | G25: 800 | H25: 725 | I25: 825 | J25: 800 | K25: 750
A26: =Assumptions!F19 -> 0.04 | G26: =G25*(1+$A26) -> 832 | H26: =H25*(1+$A26) -> 754 | I26: =I25*(1+$A26) -> 858 | J26: =J25*(1+$A26) -> 832 | K26: =K25*(1+$A26) -> 780
A27: =Assumptions!F20 -> -0.04 | G27: =G25*(1+$A27) -> 768 | H27: =H25*(1+$A27) -> 696 | I27: =I25*(1+$A27) -> 792 | J27: =J25*(1+$A27) -> 768 | K27: =K25*(1+$A27) -> 720
B30: Sales Volume Growth | D30: 1 | G30: =CHOOSE($D$30,G32,G33,G34) -> 0.05 | H30: =CHOOSE($D$30,H32,H33,H34) -> 0.04 | I30: =CHOOSE($D$30,I32,I33,I34) -> 0.04 | J30: =CHOOSE($D$30,J32,J33,J34) -> 0.04 | K30: =CHOOSE($D$30,K32,K33,K34) -> 0.04
C32: =C14 -> Base Case | G32: 0.05 | H32: 0.04 | I32: 0.04 | J32: 0.04 | K32: 0.04
C33: =C15 -> Best Case | G33: 0.05 | H33: 0.04 | I33: 0.05 | J33: 0.05 | K33: 0.04
C34: =C16 -> Worst Case | G34: 0.04 | H34: 0.04 | I34: 0.03 | J34: 0.03 | K34: 0.02
